__init__.py
ogc_reader.py
test.py
OGCReader-0.0.3.dist-info/METADATA
OGCReader-0.0.3.dist-info/WHEEL
OGCReader-0.0.3.dist-info/top_level.txt
OGCReader-0.0.3.dist-info/RECORD
