Metadata-Version: 2.1
Name: OGCReader
Version: 0.0.3
Summary: OGC Reader
Home-page: https://github.com/williamccondori/OGCReader
Author: William Condori
Author-email: williamccondori@gmail.com
License: MIT
